Metadata-Version: 2.1
Name: ExprSolver
Version: 0.0.0
Summary: Include function to solve expressions
Home-page: UNKNOWN
Author: Vikas Saini
Author-email: sainivk565@gmail.com
License: MIT
Keywords: ExprSolvers
Platform: UNKNOWN
Classifier: Development Status :: 5 - Production/Stable
Classifier: Intended Audience :: Education
Classifier: Operating System :: Microsoft :: Windows :: Windows 10
Classifier: License :: OSI Approved :: MIT License
Classifier: Programming Language :: Python :: 3
License-File: LICENSE.txt
